ad/__init__.py
ad/helpers.py
ad/main.py
ad/ops.py
ad/pipelines.py
ad/step.py
ad/storage.py
ad/version.py
src/__init__.py
src/main.py
src/storage.py
src/version.py
ad_components-0.1.39.dist-info/METADATA
ad_components-0.1.39.dist-info/WHEEL
ad_components-0.1.39.dist-info/entry_points.txt
ad_components-0.1.39.dist-info/top_level.txt
ad_components-0.1.39.dist-info/RECORD
