Metadata-Version: 2.1
Name: ad-components
Version: 0.1.39
Summary: Accelerated Discovery Reusable Components.
Home-page: https://github.ibm.com/Accelerated-Discovery/Discovery-Platform
Classifier: Development Status :: 5 - Production/Stable
Classifier: Intended Audience :: Developers
Classifier: Operating System :: OS Independent
Classifier: Programming Language :: Python :: 3
Classifier: Programming Language :: Python :: 3.8
Classifier: Programming Language :: Python :: 3.9
Classifier: Programming Language :: Python :: 3.10
Classifier: Topic :: Software Development
